memhack.py
memhack-1.0.0.dist-info/LICENSE
memhack-1.0.0.dist-info/METADATA
memhack-1.0.0.dist-info/WHEEL
memhack-1.0.0.dist-info/top_level.txt
memhack-1.0.0.dist-info/RECORD
