Metadata-Version: 2.1
Name: memhack
Version: 1.0.0
Summary: Arbitrary RAM Access
Home-page: https://github.com/szabolcsdombi/memhack/
Author: Szabolcs Dombi
Author-email: szabolcs@szabolcsdombi.com
License: MIT
Project-URL: Source, https://github.com/szabolcsdombi/memhack/
Project-URL: Bug Tracker, https://github.com/szabolcsdombi/memhack/issues/
Keywords: ram,memory,mem,pointer,ptr,heap
Platform: any
Classifier: Programming Language :: Python :: 3
Classifier: License :: OSI Approved :: MIT License
Classifier: Operating System :: OS Independent
Classifier: Development Status :: 5 - Production/Stable
Classifier: Topic :: Software Development
Classifier: Topic :: Software Development :: Debuggers
Classifier: Topic :: Utilities
License-File: LICENSE
